<annotation>
	<folder>images</folder>
	<filename>0121.jpg</filename>
	<path>C:\Users\admin\Desktop\data for final project\lemon\images\0121.jpg</path>
	<source>
		<database>Unknown</database>
	</source>
	<size>
		<width>237</width>
		<height>213</height>
		<depth>3</depth>
	</size>
	<segmented>0</segmented>
	<object>
		<name>Lemon</name>
		<pose>Unspecified</pose>
		<truncated>0</truncated>
		<difficult>0</difficult>
		<bndbox>
			<xmin>127</xmin>
			<ymin>65</ymin>
			<xmax>188</xmax>
			<ymax>145</ymax>
		</bndbox>
	</object>
	<object>
		<name>Lemon</name>
		<pose>Unspecified</pose>
		<truncated>0</truncated>
		<difficult>0</difficult>
		<bndbox>
			<xmin>59</xmin>
			<ymin>40</ymin>
			<xmax>130</xmax>
			<ymax>116</ymax>
		</bndbox>
	</object>
	<object>
		<name>Lemon</name>
		<pose>Unspecified</pose>
		<truncated>0</truncated>
		<difficult>0</difficult>
		<bndbox>
			<xmin>73</xmin>
			<ymin>107</ymin>
			<xmax>154</xmax>
			<ymax>179</ymax>
		</bndbox>
	</object>
	<object>
		<name>Lemon</name>
		<pose>Unspecified</pose>
		<truncated>0</truncated>
		<difficult>0</difficult>
		<bndbox>
			<xmin>28</xmin>
			<ymin>92</ymin>
			<xmax>96</xmax>
			<ymax>167</ymax>
		</bndbox>
	</object>
</annotation>
