<annotation>
	<folder>images</folder>
	<filename>0021.jpg</filename>
	<path>C:\Users\admin\Desktop\data for final project\Lettuce\images\0021.jpg</path>
	<source>
		<database>Unknown</database>
	</source>
	<size>
		<width>243</width>
		<height>207</height>
		<depth>3</depth>
	</size>
	<segmented>0</segmented>
	<object>
		<name>Lettuce</name>
		<pose>Unspecified</pose>
		<truncated>0</truncated>
		<difficult>0</difficult>
		<bndbox>
			<xmin>8</xmin>
			<ymin>12</ymin>
			<xmax>228</xmax>
			<ymax>181</ymax>
		</bndbox>
	</object>
</annotation>
